{
  "containers": [
    {
      "name": "openclaw-mission-control-mission-control-1",
      "image": "openclaw-mission-control-mission-control",
      "state": "running",
      "status": "Up 3 seconds (health: starting)"
    },
    {
      "name": "openclaw-pa62-openclaw-1",
      "image": "ghcr.io/hostinger/hvps-openclaw@sha256:c677c4994dfc34827e99f422f672e7164e0a82716182874fdef5967de02747ea",
      "state": "running",
      "status": "Up 27 hours (healthy)"
    }
  ],
  "disk": {
    "usedBytes": 67638710272,
    "availBytes": 35232608256,
    "totalBytes": 102888095744,
    "percent": 66
  },
  "cronErrors": [
    {
      "name": "Daily Gambling Data Refresh",
      "errors": 1
    }
  ],
  "cronTotal": 30,
  "gatewayUp": true,
  "updatedAt": 1775412637090
}