{
  "containers": [
    {
      "name": "openclaw-pa62-openclaw-1",
      "image": "ghcr.io/openclaw/openclaw:latest",
      "state": "running",
      "status": "Up 7 seconds (health: starting)"
    },
    {
      "name": "keen_golick",
      "image": "ghcr.io/hostinger/hvps-openclaw@sha256:b3c2f0d055093f64cdca374a3b718c97338def4093671afe3ab8fa153637bc69",
      "state": "running",
      "status": "Up 2 hours"
    },
    {
      "name": "openclaw-mission-control-mission-control-1",
      "image": "openclaw-mission-control-mission-control",
      "state": "running",
      "status": "Up 27 hours (healthy)"
    }
  ],
  "disk": {
    "usedBytes": 55193882624,
    "availBytes": 47677435904,
    "totalBytes": 102888095744,
    "percent": 54
  },
  "cronErrors": [
    {
      "name": "Daily Log Rotation",
      "errors": 1
    }
  ],
  "cronTotal": 30,
  "gatewayUp": false,
  "updatedAt": 1775522316132
}